hotpatch/__init__.py
hotpatch/cli/__init__.py
hotpatch/cli/hotpatch_cli.py
hotpatch-0.0.1.dist-info/METADATA
hotpatch-0.0.1.dist-info/WHEEL
hotpatch-0.0.1.dist-info/entry_points.txt
hotpatch-0.0.1.dist-info/top_level.txt
hotpatch-0.0.1.dist-info/RECORD
