Metadata-Version: 2.1
Name: hotpatch
Version: 0.0.1
Summary: Apply hot patches for running processes without restarting
Home-page: https://github.com/tobegit3hub/hotpatch
Author: tobe
Author-email: tobeg3oogle@gmail.com
License: UNKNOWN
Platform: UNKNOWN
